chemprop_contrib/__init__.py
chemprop_contrib/moe_regressor/LICENSE
chemprop_contrib/moe_regressor/README.md
chemprop_contrib/moe_regressor/__init__.py
chemprop_contrib/moe_regressor/expert_mixture_ffn.py
chemprop_contrib/moe_regressor/test_expert_mixture_ffn.py
chemprop_contrib-2025.11.1.dist-info/METADATA
chemprop_contrib-2025.11.1.dist-info/WHEEL
chemprop_contrib-2025.11.1.dist-info/top_level.txt
chemprop_contrib-2025.11.1.dist-info/RECORD
