Metadata-Version: 2.4
Name: chemprop-contrib
Version: 2025.11.1
Summary: Community contributions to chemprop
Author-email: The Chemprop Development Team <chemprop@mit.edu>
License: MIT unless otherwise noted in individual contribution files
Project-URL: source, https://github.com/chemprop/chemprop-contrib
Project-URL: PyPi, https://pypi.org/project/chemprop/
Keywords: chemistry,machine learning,property prediction,message passing neural network,graph neural network,drug discovery
Classifier: Programming Language :: Python :: 3
Classifier: Programming Language :: Python :: 3.11
Classifier: Operating System :: OS Independent
Requires-Python: >=3.11
Requires-Dist: chemprop
